{"id":"6s8z","dependencies":[{"name":"./style.css","dynamic":true,"parent":"C:\\Users\\Administrator\\Desktop\\TaiChi\\src\\index.html","resolved":"C:\\Users\\Administrator\\Desktop\\TaiChi\\src\\style.css"},{"name":"./1.js","dynamic":true,"parent":"C:\\Users\\Administrator\\Desktop\\TaiChi\\src\\index.html","resolved":"C:\\Users\\Administrator\\Desktop\\TaiChi\\src\\1.js"}],"generated":{"html":"<!DOCTYPE html>\r\n<html lang=\"en\">\r\n\r\n<head>\r\n    <meta charset=\"UTF-8\">\r\n    <meta http-equiv=\"X-UA-Compatible\" content=\"IE=edge\">\r\n    <meta name=\"viewport\" content=\"width=device-width,initial-scale=1,minimum-scale=1,maximum-scale=1,user-scalable=no,viewport-fit=cover\">\r\n    <meta http-equiv=\"X-UA-Compatible\" content=\"ie=edge\">\r\n    <title>TaiChi</title>\r\n    <link rel=\"stylesheet\" href=\"dist/ff669bf02ee9f67c911e32e5fab3d6da.css\">\r\n\r\n</head>\r\n\r\n<body>\r\n    <style id=\"style\">\r\n    </style>\r\n\r\n    <div id=\"html\"></div>\r\n    <div id=\"div1Wrapper\">\r\n        <div id=\"div1\">\r\n        </div>\r\n    </div>\r\n    <script src=\"dist/5971459dcac4cd2434b0b9aba25945a5.js\">\r\n    </script>\r\n</body>\r\n\r\n</html>"},"hash":"36ffb5299666b46e93ec06469774fd70","cacheData":{}}